tests/fixtures/__init__.py
tests/fixtures/secrets/__init__.py
tests/fixtures/secrets/secrets.py
tests/mock/__init__.py
tests/mock/cache_timer.py
tests/mock/request.py
walmart_auth/__init__.py
walmart_auth/auth.py
walmart_auth/session.py
walmart_auth/bin/__init__.py
walmart_auth/bin/helpers.py
walmart_auth/bin/session.py
walmart_auth/signed_headers_factory/__init__.py
walmart_auth/signed_headers_factory/cache_timer.py
walmart_auth/signed_headers_factory/helpers.py
walmart_auth/signed_headers_factory/sign.py
walmart_auth/signed_headers_factory/signed_headers_factory.py
requests_walmart_auth-1.0.1.dist-info/LICENSE
requests_walmart_auth-1.0.1.dist-info/METADATA
requests_walmart_auth-1.0.1.dist-info/WHEEL
requests_walmart_auth-1.0.1.dist-info/entry_points.txt
requests_walmart_auth-1.0.1.dist-info/top_level.txt
requests_walmart_auth-1.0.1.dist-info/RECORD
