Metadata-Version: 2.1
Name: requests-walmart-auth
Version: 1.0.1
Summary: python requests support for the Walmart Affiliate Marketplace (REST) API required Additional Headers
Home-page: https://github.com/Terrabits/requests-walmart-auth
Author: Nick Lalic
Author-email: nick.lalic@gmail.com
License: MIT
Platform: UNKNOWN
Requires-Python: >=3.7
License-File: LICENSE
Requires-Dist: pycryptodome (~=3.14.1)
Requires-Dist: requests (~=2.27.1)
Provides-Extra: dev
Requires-Dist: twine ; extra == 'dev'
Requires-Dist: wheel ; extra == 'dev'
